{
  "forensic_id": "ALERT_1762713283609",
  "timestamp": 1762713277.670399,
  "datetime": "2025-11-10T00:04:37.670399",
  "event_type": "clipboard_copy",
  "detection_methods": [
    "rule_based",
    "ml_based"
  ],
  "reasons": [
    "Rule 1: Clipboard copy exceeds threshold: 300KB > 200KB",
    "ML anomaly score: 1.000 (threshold: 0.5)"
  ],
  "severity": "high",
  "ml_score": 1.0,
  "event_details": {
    "event_type": "clipboard_copy",
    "timestamp": 1762713277.670399,
    "size_bytes": 307200,
    "size_kb": 300,
    "content_preview": "[300KB of data]",
    "source": "vnc_client"
  },
  "containment_status": "pending",
  "hash": "5c4bc67c45716abfe8f14e79055dcc3a6bb57df7a80142b0db3d33d79201714d"
}